oslom/__init__.py
oslom/runner.py
oslom_runner-1.5.dist-info/LICENSE
oslom_runner-1.5.dist-info/METADATA
oslom_runner-1.5.dist-info/WHEEL
oslom_runner-1.5.dist-info/entry_points.txt
oslom_runner-1.5.dist-info/top_level.txt
oslom_runner-1.5.dist-info/RECORD
