Metadata-Version: 2.1
Name: oslom-runner
Version: 1.5
Summary: An OSLOM (community finding) runner for Python
Home-page: https://github.com/hhromic/python-oslom-runner
Author: Hugo Hromic
Author-email: hhromic@gmail.com
Maintainer: Hugo Hromic
Maintainer-email: hhromic@gmail.com
License: Apache-2.0
Download-URL: https://github.com/hhromic/python-oslom-runner/tarball/1.5
Keywords: oslom,runner,clustering,communities
Platform: all
Classifier: Environment :: Console
Requires: simplejson
Provides: oslom
Requires-Dist: simplejson
